warcit/__init__.py
warcit/base.py
warcit/converter.py
warcit/default-conversion-rules.yaml
warcit/warcit.py
warcit-0.4.0.dist-info/LICENSE
warcit-0.4.0.dist-info/METADATA
warcit-0.4.0.dist-info/WHEEL
warcit-0.4.0.dist-info/entry_points.txt
warcit-0.4.0.dist-info/top_level.txt
warcit-0.4.0.dist-info/zip-safe
warcit-0.4.0.dist-info/RECORD
