Metadata-Version: 2.1
Name: warcit
Version: 0.4.0
Summary: Convert Directories, Files and Zip Files to Web Archives (WARC)
Home-page: https://github.com/webrecorder/warcit
Author: Ilya Kreymer
Author-email: ikreymer@gmail.com
License: Apache 2.0
Platform: UNKNOWN
Classifier: Development Status :: 4 - Beta
Classifier: Environment :: Web Environment
Classifier: License :: OSI Approved :: Apache Software License
Classifier: Programming Language :: Python :: 3
Classifier: Programming Language :: Python :: 3.4
Classifier: Programming Language :: Python :: 3.5
Classifier: Programming Language :: Python :: 3.6
Classifier: Topic :: Software Development :: Libraries :: Python Modules
Classifier: Topic :: Utilities
Provides: warcit
Requires-Dist: warcio (>=1.6.1)
Requires-Dist: cchardet
Requires-Dist: pyyaml
